[
  {
    "request": {
      "method": "POST",
      "path": "/v1/projects/__PROJECT_REF__/custom-hostname/initialize",
      "query": {},
      "headers": {
        "accept-encoding": "gzip",
        "authorization": "Bearer __ACCESS_TOKEN__",
        "content-length": "41",
        "content-type": "application/json",
        "host": "localhost:__PORT__",
        "user-agent": "SupabaseCLI/2.84.2"
      },
      "body": {
        "custom_hostname": "www.urgsimurksi.xyz"
      }
    },
    "response": {
      "status": 544,
      "headers": {
        "content-type": "application/json; charset=utf-8",
        "x-gotrue-id": "__UUID__",
        "x-ratelimit-limit": "10",
        "x-ratelimit-remaining": "9",
        "x-ratelimit-reset": "60"
      },
      "body": {
        "message": "Delete the custom hostname associated with your project before attempting to create a new one."
      }
    }
  }
]
